MANIFEST.in
MIT_LICENSE
README.md
requirements.txt
setup.cfg
setup.py
metrics.bumpversion.egg-info/PKG-INFO
metrics.bumpversion.egg-info/SOURCES.txt
metrics.bumpversion.egg-info/dependency_links.txt
metrics.bumpversion.egg-info/entry_points.txt
metrics.bumpversion.egg-info/top_level.txt
metrics_bumpversion/__init__.py
metrics_bumpversion/info.py