Metadata-Version: 1.1
Name: metrics.bumpversion
Version: 0.0.1
Summary: plugin for the metrics package (extracts version from .bumpversion.cfg)
Home-page: https://github.com/markfink/metrics.bumpversion/
Author: Mark Fink
Author-email: mark@mark-fink.de
License: MIT
Platform: UNKNOWN
Classifier: Natural Language :: English
Classifier: Intended Audience :: Developers
Classifier: Environment :: Console
Classifier: License :: OSI Approved :: MIT License
Classifier: Programming Language :: Python :: 2.7
Classifier: Programming Language :: Python :: 3.6
